{
  "characters": [
    {
      "id": 1,
      "name": "America Chavez (Young Avengers)",
      "image": "#",
      "rarity": 4,
      "powerOneLevel": 0,
      "powerTwoLevel": 0,
      "powerThreeLevel": 0,
      "powerOneColor": "red",
      "powerTwoColor": "yellow",
      "powerThreeColor": "green",
      "feedeeId": 69,
      "feederId": 0,
      "charLevel": 70
    },
    {
      "id": 2,
      "name": "Angel (All New X-Men)",
      "image": "#",
      "rarity": 3,
      "powerOneLevel": 0,
      "powerTwoLevel": 0,
      "powerThreeLevel": 0,
      "powerOneColor": "blue",
      "powerTwoColor": "black",
      "powerThreeColor": "green",
      "feedeeId": 68,
      "feederId": 0,
      "charLevel": 40
    },
    {
      "id": 3,
      "name": "Ant-Man (Scott Lang)",
      "image": "#",
      "rarity": 4,
      "powerOneLevel": 0,
      "powerTwoLevel": 0,
      "powerThreeLevel": 0,
      "powerOneColor": "purple",
      "powerTwoColor": "blue",
      "powerThreeColor": "yellow",
      "feedeeId": 133,
      "feederId": 115,
      "charLevel": 70
    },
    {
      "id": 4,
      "name": "Ares (Dark Avengers)",
      "image": "#",
      "rarity": 2,
      "powerOneLevel": 0,
      "powerTwoLevel": 0,
      "powerThreeLevel": 0,
      "powerOneColor": "green",
      "powerTwoColor": "red",
      "powerThreeColor": "yellow",
      "feedeeId": 97,
      "feederId": 0,
      "charLevel": 15
    },
    {
      "id": 5,
      "name": "Beast (Classic)",
      "image": "#",
      "rarity": 3,
      "powerOneLevel": 0,
      "powerTwoLevel": 0,
      "powerThreeLevel": 0,
      "powerOneColor": "blue",
      "powerTwoColor": "green",
      "powerThreeColor": "yellow",
      "feedeeId": 68,
      "feederId": 0,
      "charLevel": 40
    },
    {
      "id": 6,
      "name": "Black Bolt (Inhuman King)",
      "image": "#",
      "rarity": 5,
      "powerOneLevel": 0,
      "powerTwoLevel": 0,
      "powerThreeLevel": 0,
      "powerOneColor": "green",
      "powerTwoColor": "black",
      "powerThreeColor": "yellow",
      "feedeeId": 0,
      "feederId": 81,
      "charLevel": 255
    },
    {
      "id": 7,
      "name": "Black Panther (Civil War)",
      "image": "#",
      "rarity": 5,
      "powerOneLevel": 0,
      "powerTwoLevel": 0,
      "powerThreeLevel": 0,
      "powerOneColor": "black",
      "powerTwoColor": "yellow",
      "powerThreeColor": "red",
      "feedeeId": 0,
      "feederId": 8,
      "charLevel": 255
    },
    {
      "id": 8,
      "name": "Black Panther (King of Wakanda)",
      "image": "#",
      "rarity": 4,
      "powerOneLevel": 0,
      "powerTwoLevel": 0,
      "powerThreeLevel": 0,
      "powerOneColor": "yellow",
      "powerTwoColor": "blue",
      "powerThreeColor": "red",
      "feedeeId": 7,
      "feederId": 0,
      "charLevel": 70
    },
    {
      "id": 9,
      "name": "Black Panther (T'Challa)",
      "image": "#",
      "rarity": 3,
      "powerOneLevel": 0,
      "powerTwoLevel": 0,
      "powerThreeLevel": 0,
      "powerOneColor": "yellow",
      "powerTwoColor": "blue",
      "powerThreeColor": "black",
      "feedeeId": 86,
      "feederId": 0,
      "charLevel": 40
    },
    {
      "id": 10,
      "name": "Black Widow (Natasha Romanoff)",
      "image": "#",
      "rarity": 5,
      "powerOneLevel": 0,
      "powerTwoLevel": 0,
      "powerThreeLevel": 0,
      "powerOneColor": "purple",
      "powerTwoColor": "red",
      "powerThreeColor": "black",
      "feedeeId": 0,
      "feederId": 11,
      "charLevel": 255
    },
    {
      "id": 11,
      "name": "Black Widow (Infinity War)",
      "image": "#",
      "rarity": 4,
      "powerOneLevel": 0,
      "powerTwoLevel": 0,
      "powerThreeLevel": 0,
      "powerOneColor": "black",
      "powerTwoColor": "purple",
      "powerThreeColor": "yellow",
      "feedeeId": 10,
      "feederId": 0,
      "charLevel": 70
    },
    {
      "id": 12,
      "name": "Black Widow (Grey Suit)",
      "image": "#",
      "rarity": 3,
      "powerOneLevel": 0,
      "powerTwoLevel": 0,
      "powerThreeLevel": 0,
      "powerOneColor": "purple",
      "powerTwoColor": "green",
      "powerThreeColor": "red",
      "feedeeId": 88,
      "feederId": 11,
      "charLevel": 70
    },
    {
      "id": 13,
      "name": "Black Widow (Original)",
      "image": "#",
      "rarity": 2,
      "powerOneLevel": 0,
      "powerTwoLevel": 0,
      "powerThreeLevel": 0,
      "powerOneColor": "purple",
      "powerTwoColor": "blue",
      "powerThreeColor": "black",
      "feedeeId": 12,
      "feederId": 0,
      "charLevel": 15
    },
    {
      "id": 14,
      "name": "Blade (Modern)",
      "image": "#",
      "rarity": 4,
      "powerOneLevel": 0,
      "powerTwoLevel": 0,
      "powerThreeLevel": 0,
      "powerOneColor": "red",
      "powerTwoColor": "green",
      "powerThreeColor": "black",
      "feedeeId": 0,
      "feederId": 15,
      "charLevel": 70
    },
    {
      "id": 15,
      "name": "Blade (Daywalker)",
      "image": "#",
      "rarity": 3,
      "powerOneLevel": 0,
      "powerTwoLevel": 0,
      "powerThreeLevel": 0,
      "powerOneColor": "black",
      "powerTwoColor": "purple",
      "powerThreeColor": "green",
      "feedeeId": 14,
      "feederId": 0,
      "charLevel": 40
    },
    {
      "id": 16,
      "name": "Bullseye (Dark Avengers)",
      "image": "#",
      "rarity": 2,
      "powerOneLevel": 0,
      "powerTwoLevel": 0,
      "powerThreeLevel": 0,
      "powerOneColor": "purple",
      "powerTwoColor": "black",
      "powerThreeColor": "green",
      "feedeeId": 17,
      "feederId": 0,
      "charLevel": 15
    },
    {
      "id": 17,
      "name": "Bullseye (Classic)",
      "image": "#",
      "rarity": 3,
      "powerOneLevel": 0,
      "powerTwoLevel": 0,
      "powerThreeLevel": 0,
      "powerOneColor": "purple",
      "powerTwoColor": "black",
      "powerThreeColor": "green",
      "feedeeId": 74,
      "feederId": 16,
      "charLevel": 40
    },
    {
      "id": 18,
      "name": "Captain America (The First Avenger)",
      "image": "#",
      "rarity": 5,
      "powerOneLevel": 0,
      "powerTwoLevel": 0,
      "powerThreeLevel": 0,
      "powerOneColor": "yellow",
      "powerTwoColor": "red",
      "powerThreeColor": "blue",
      "feedeeId": 0,
      "feederId": 91,
      "charLevel": 255
    },
    {
      "id": 19,
      "name": "Captain America (Infinity War)",
      "image": "#",
      "rarity": 5,
      "powerOneLevel": 0,
      "powerTwoLevel": 0,
      "powerThreeLevel": 0,
      "powerOneColor": "red",
      "powerTwoColor": "purple",
      "powerThreeColor": "yellow",
      "feedeeId": 0,
      "feederId": 135,
      "charLevel": 255
    },
    {
      "id": 20,
      "name": "Captain America (Super Soldier)",
      "image": "#",
      "rarity": 3,
      "powerOneLevel": 0,
      "powerTwoLevel": 0,
      "powerThreeLevel": 0,
      "powerOneColor": "yellow",
      "powerTwoColor": "red",
      "powerThreeColor": "blue",
      "feedeeId": 0,
      "feederId": 21,
      "charLevel": 40
    },
    {
      "id": 21,
      "name": "Captain America (Steve Rogers)",
      "image": "#",
      "rarity": 2,
      "powerOneLevel": 0,
      "powerTwoLevel": 0,
      "powerThreeLevel": 0,
      "powerOneColor": "yellow",
      "powerTwoColor": "red",
      "powerThreeColor": "blue",
      "feedeeId": 20,
      "feederId": 0,
      "charLevel": 15
    },
    {
      "id": 22,
      "name": "Captain Marvel (Galactic Warrior)",
      "image": "#",
      "rarity": 5,
      "powerOneLevel": 0,
      "powerTwoLevel": 0,
      "powerThreeLevel": 0,
      "powerOneColor": "red",
      "powerTwoColor": "green",
      "powerThreeColor": "yellow",
      "feedeeId": 0,
      "feederId": 23,
      "charLevel": 255
    },
    {
      "id": 23,
      "name": "Captain Marvel (Carol Danvers)",
      "image": "#",
      "rarity": 4,
      "powerOneLevel": 0,
      "powerTwoLevel": 0,
      "powerThreeLevel": 0,
      "powerOneColor": "black",
      "powerTwoColor": "yellow",
      "powerThreeColor": "green",
      "feedeeId": 22,
      "feederId": 24,
      "charLevel": 70
    },
    {
      "id": 24,
      "name": "Captain Marvel (Modern)",
      "image": "#",
      "rarity": 3,
      "powerOneLevel": 0,
      "powerTwoLevel": 0,
      "powerThreeLevel": 0,
      "powerOneColor": "black",
      "powerTwoColor": "yellow",
      "powerThreeColor": "green",
      "feedeeId": 23,
      "feederId": 25,
      "charLevel": 40
    },
    {
      "id": 25,
      "name": "Captain Marvel (Ms. Marvel)",
      "image": "#",
      "rarity": 2,
      "powerOneLevel": 0,
      "powerTwoLevel": 0,
      "powerThreeLevel": 0,
      "powerOneColor": "red",
      "powerTwoColor": "black",
      "powerThreeColor": "yellow",
      "feedeeId": 24,
      "feederId": 0,
      "charLevel": 15
    },
    {
      "id": 26,
      "name": "Carnage (Cletus Kassady)",
      "image": "#",
      "rarity": 4,
      "powerOneLevel": 0,
      "powerTwoLevel": 0,
      "powerThreeLevel": 0,
      "powerOneColor": "red",
      "powerTwoColor": "black",
      "powerThreeColor": "green",
      "feedeeId": 38,
      "feederId": 37,
      "charLevel": 70
    },
    {
      "id": 27,
      "name": "Colossus (Classic)",
      "image": "#",
      "rarity": 3,
      "powerOneLevel": 0,
      "powerTwoLevel": 0,
      "powerThreeLevel": 0,
      "powerOneColor": "yellow",
      "powerTwoColor": "red",
      "powerThreeColor": "black",
      "feedeeId": 139,
      "feederId": 0,
      "charLevel": 40
    },
    {
      "id": 28,
      "name": "Cyclops (Classic)",
      "image": "#",
      "rarity": 4,
      "powerOneLevel": 0,
      "powerTwoLevel": 0,
      "powerThreeLevel": 0,
      "powerOneColor": "red",
      "powerTwoColor": "yellow",
      "powerThreeColor": "blue",
      "feedeeId": 0,
      "feederId": 29,
      "charLevel": 70
    },
    {
      "id": 29,
      "name": "Cyclops (Uncanny X-Men)",
      "image": "#",
      "rarity": 3,
      "powerOneLevel": 0,
      "powerTwoLevel": 0,
      "powerThreeLevel": 0,
      "powerOneColor": "red",
      "powerTwoColor": "yellow",
      "powerThreeColor": "black",
      "feedeeId": 28,
      "feederId": 0,
      "charLevel": 40
    },
    {
      "id": 30,
      "name": "Daken (Dark Avengers)",
      "image": "#",
      "rarity": 2,
      "powerOneLevel": 0,
      "powerTwoLevel": 0,
      "powerThreeLevel": 0,
      "powerOneColor": "purple",
      "powerTwoColor": "black",
      "powerThreeColor": "blue",
      "feedeeId": 31,
      "feederId": 0,
      "charLevel": 15
    },
    {
      "id": 31,
      "name": "Daken (Classic)",
      "image": "#",
      "rarity": 3,
      "powerOneLevel": 0,
      "powerTwoLevel": 0,
      "powerThreeLevel": 0,
      "powerOneColor": "red",
      "powerTwoColor": "yellow",
      "powerThreeColor": "black",
      "feedeeId": 140,
      "feederId": 30,
      "charLevel": 40
    },
    {
      "id": 32,
      "name": "Daredevil (Man Without Fear)",
      "image": "#",
      "rarity": 3,
      "powerOneLevel": 0,
      "powerTwoLevel": 0,
      "powerThreeLevel": 0,
      "powerOneColor": "purple",
      "powerTwoColor": "blue",
      "powerThreeColor": "red",
      "feedeeId": 43,
      "feederId": 0,
      "charLevel": 40
    },
    {
      "id": 33,
      "name": "Daredevil (Matt Murdock)",
      "image": "#",
      "rarity": 5,
      "powerOneLevel": 0,
      "powerTwoLevel": 0,
      "powerThreeLevel": 0,
      "powerOneColor": "yellow",
      "powerTwoColor": "purple",
      "powerThreeColor": "green",
      "feedeeId": 0,
      "feederId": 74,
      "charLevel": 255
    },
    {
      "id": 34,
      "name": "Deadpool (It's Me, Deadpool!)",
      "image": "#",
      "rarity": 3,
      "powerOneLevel": 0,
      "powerTwoLevel": 0,
      "powerThreeLevel": 0,
      "powerOneColor": "red",
      "powerTwoColor": "purple",
      "powerThreeColor": "black",
      "feedeeId": 35,
      "feederId": 0,
      "charLevel": 255
    },
    {
      "id": 35,
      "name": "Deadpool (Uncanny X-Force)",
      "image": "#",
      "rarity": 4,
      "powerOneLevel": 0,
      "powerTwoLevel": 0,
      "powerThreeLevel": 0,
      "powerOneColor": "red",
      "powerTwoColor": "black",
      "powerThreeColor": "purple",
      "feedeeId": 0,
      "feederId": 34,
      "charLevel": 255
    },
    {
      "id": 36,
      "name": "Doctor Doom (Classic)",
      "image": "#",
      "rarity": 5,
      "powerOneLevel": 0,
      "powerTwoLevel": 0,
      "powerThreeLevel": 0,
      "powerOneColor": "black",
      "powerTwoColor": "blue",
      "powerThreeColor": "purple",
      "feedeeId": 61,
      "feederId": 0,
      "charLevel": 40
    },
    {
      "id": 37,
      "name": "Doctor Octopus (Otto Octavius)",
      "image": "#",
      "rarity": 5,
      "powerOneLevel": 0,
      "powerTwoLevel": 0,
      "powerThreeLevel": 0,
      "powerOneColor": "blue",
      "powerTwoColor": "black",
      "powerThreeColor": "green",
      "feedeeId": 26,
      "feederId": 0,
      "charLevel": 255
    },
    {
      "id": 38,
      "name": "Doctor Octopus (Classic)",
      "image": "#",
      "rarity": 5,
      "powerOneLevel": 0,
      "powerTwoLevel": 0,
      "powerThreeLevel": 0,
      "powerOneColor": "black",
      "powerTwoColor": "blue",
      "powerThreeColor": "green",
      "feedeeId": 0,
      "feederId": 26,
      "charLevel": 255
    },
    {
      "id": 39,
      "name": "Doctor Strange (Stephen Strange)",
      "image": "#",
      "rarity": 3,
      "powerOneLevel": 0,
      "powerTwoLevel": 0,
      "powerThreeLevel": 0,
      "powerOneColor": "blue",
      "powerTwoColor": "purple",
      "powerThreeColor": "yellow",
      "feedeeId": 89,
      "feederId": 0,
      "charLevel": 40
    },
    {
      "id": 40,
      "name": "Doctor Strange (Sorcerer Supreme)",
      "image": "#",
      "rarity": 5,
      "powerOneLevel": 0,
      "powerTwoLevel": 0,
      "powerThreeLevel": 0,
      "powerOneColor": "blue",
      "powerTwoColor": "purple",
      "powerThreeColor": "yellow",
      "feedeeId": 0,
      "feederId": 85,
      "charLevel": 255
    },
    {
      "id": 41,
      "name": "Drax (The Destroyer)",
      "image": "#",
      "rarity": 4,
      "powerOneLevel": 0,
      "powerTwoLevel": 0,
      "powerThreeLevel": 0,
      "powerOneColor": "black",
      "powerTwoColor": "purple",
      "powerThreeColor": "red",
      "feedeeId": 116,
      "feederId": 99,
      "charLevel": 70
    },
    {
      "id": 42,
      "name": "Elektra (Assassin)",
      "image": "#",
      "rarity": 3,
      "powerOneLevel": 0,
      "powerTwoLevel": 0,
      "powerThreeLevel": 0,
      "powerOneColor": "purple",
      "powerTwoColor": "black",
      "powerThreeColor": "red",
      "feedeeId": 43,
      "feederId": 0,
      "charLevel": 40
    },
    {
      "id": 43,
      "name": "Elektra (Unkillable)",
      "image": "#",
      "rarity": 5,
      "powerOneLevel": 0,
      "powerTwoLevel": 0,
      "powerThreeLevel": 0,
      "powerOneColor": "purple",
      "powerTwoColor": "black",
      "powerThreeColor": "red",
      "feedeeId": 0,
      "feederId": 32,
      "charLevel": 70
    },
    {
      "id": 44,
      "name": "Gambit (Modern)",
      "image": "#",
      "rarity": 5,
      "powerOneLevel": 0,
      "powerTwoLevel": 0,
      "powerThreeLevel": 0,
      "powerOneColor": "purple",
      "powerTwoColor": "red",
      "powerThreeColor": "black",
      "feedeeId": 100,
      "feederId": 0,
      "charLevel": 40
    },
    {
      "id": 45,
      "name": "Gamora (Guardians of the Galaxy)",
      "image": "#",
      "rarity": 3,
      "powerOneLevel": 0,
      "powerTwoLevel": 0,
      "powerThreeLevel": 0,
      "powerOneColor": "green",
      "powerTwoColor": "red",
      "powerThreeColor": "black",
      "feedeeId": 117,
      "feederId": 0,
      "charLevel": 40
    },
    {
      "id": 46,
      "name": "Gamora (Awesome Mix Volume 2)",
      "image": "#",
      "rarity": 4,
      "powerOneLevel": 0,
      "powerTwoLevel": 0,
      "powerThreeLevel": 0,
      "powerOneColor": "red",
      "powerTwoColor": "black",
      "powerThreeColor": "blue",
      "feedeeId": 121,
      "feederId": 0,
      "charLevel": 70
    },
    {
      "id": 47,
      "name": "Ghost Rider (Robbie Reyes)",
      "image": "#",
      "rarity": 5,
      "powerOneLevel": 0,
      "powerTwoLevel": 0,
      "powerThreeLevel": 0,
      "powerOneColor": "green",
      "powerTwoColor": "red",
      "powerThreeColor": "black",
      "feedeeId": 0,
      "feederId": 48,
      "charLevel": 255
    },
    {
      "id": 48,
      "name": "Ghost Rider (Johnny Blaze)",
      "image": "#",
      "rarity": 4,
      "powerOneLevel": 0,
      "powerTwoLevel": 0,
      "powerThreeLevel": 0,
      "powerOneColor": "green",
      "powerTwoColor": "red",
      "powerThreeColor": "black",
      "feedeeId": 47,
      "feederId": 56,
      "charLevel": 70
    },
    {
      "id": 49,
      "name": "Green Goblin (Norman Osborn)",
      "image": "#",
      "rarity": 5,
      "powerOneLevel": 0,
      "powerTwoLevel": 0,
      "powerThreeLevel": 0,
      "powerOneColor": "black",
      "powerTwoColor": "purple",
      "powerThreeColor": "yellow",
      "feedeeId": 0,
      "feederId": 103,
      "charLevel": 255
    },
    {
      "id": 50,
      "name": "Gwenpool (Gwen Poole)",
      "image": "#",
      "rarity": 4,
      "powerOneLevel": 0,
      "powerTwoLevel": 0,
      "powerThreeLevel": 0,
      "powerOneColor": "purple",
      "powerTwoColor": "black",
      "powerThreeColor": "green",
      "feedeeId": 0,
      "feederId": 103,
      "charLevel": 70
    },
    {
      "id": 51,
      "name": "Hawkeye (Clint Barton)",
      "image": "#",
      "rarity": 5,
      "powerOneLevel": 0,
      "powerTwoLevel": 0,
      "powerThreeLevel": 0,
      "powerOneColor": "purple",
      "powerTwoColor": "blue",
      "powerThreeColor": "red",
      "feedeeId": 0,
      "feederId": 72,
      "charLevel": 255
    },
    {
      "id": 52,
      "name": "Hawkeye (Hawkguy)",
      "image": "#",
      "rarity": 5,
      "powerOneLevel": 0,
      "powerTwoLevel": 0,
      "powerThreeLevel": 0,
      "powerOneColor": "purple",
      "powerTwoColor": "blue",
      "powerThreeColor": "black",
      "feedeeId": 72,
      "feederId": 53,
      "charLevel": 15
    },
    {
      "id": 53,
      "name": "Hawkeye (Modern)",
      "image": "#",
      "rarity": 2,
      "powerOneLevel": 0,
      "powerTwoLevel": 0,
      "powerThreeLevel": 0,
      "powerOneColor": "blue",
      "powerTwoColor": "red",
      "powerThreeColor": "purple",
      "feedeeId": 52,
      "feederId": 0,
      "charLevel": 15
    },
    {
      "id": 54,
      "name": "Human Torch (Johnny Storm)",
      "image": "#",
      "rarity": 2,
      "powerOneLevel": 0,
      "powerTwoLevel": 0,
      "powerThreeLevel": 0,
      "powerOneColor": "red",
      "powerTwoColor": "black",
      "powerThreeColor": "green",
      "feedeeId": 55,
      "feederId": 0,
      "charLevel": 15
    },
    {
      "id": 55,
      "name": "Human Torch (Classic)",
      "image": "#",
      "rarity": 3,
      "powerOneLevel": 0,
      "powerTwoLevel": 0,
      "powerThreeLevel": 0,
      "powerOneColor": "red",
      "powerTwoColor": "black",
      "powerThreeColor": "green",
      "feedeeId": 123,
      "feederId": 54,
      "charLevel": 40
    },
    {
      "id": 56,
      "name": "The Hood (Classic)",
      "image": "#",
      "rarity": 3,
      "powerOneLevel": 0,
      "powerTwoLevel": 0,
      "powerThreeLevel": 0,
      "powerOneColor": "yellow",
      "powerTwoColor": "blue",
      "powerThreeColor": "black",
      "feedeeId": 48,
      "feederId": 0,
      "charLevel": 40
    },
    {
      "id": 57,
      "name": "The Hulk (Indestructible)",
      "image": "#",
      "rarity": 3,
      "powerOneLevel": 0,
      "powerTwoLevel": 0,
      "powerThreeLevel": 0,
      "powerOneColor": "red",
      "powerTwoColor": "black",
      "powerThreeColor": "green",
      "feedeeId": 58,
      "feederId": 84,
      "charLevel": 40
    },
    {
      "id": 58,
      "name": "The Hulk (Totally Awesome)",
      "image": "#",
      "rarity": 4,
      "powerOneLevel": 0,
      "powerTwoLevel": 0,
      "powerThreeLevel": 0,
      "powerOneColor": "green",
      "powerTwoColor": "blue",
      "powerThreeColor": "black",
      "feedeeId": 0,
      "feederId": 57,
      "charLevel": 70
    },
    {
      "id": 59,
      "name": "The Hulk (Main Event)",
      "image": "#",
      "rarity": 4,
      "powerOneLevel": 0,
      "powerTwoLevel": 0,
      "powerThreeLevel": 0,
      "powerOneColor": "green",
      "powerTwoColor": "purple",
      "powerThreeColor": "yellow",
      "feedeeId": 75,
      "feederId": 0,
      "charLevel": 70
    },
    {
      "id": 60,
      "name": "Iceman (All New X-Men)",
      "image": "#",
      "rarity": 4,
      "powerOneLevel": 0,
      "powerTwoLevel": 0,
      "powerThreeLevel": 0,
      "powerOneColor": "green",
      "powerTwoColor": "blue",
      "powerThreeColor": "purple",
      "feedeeId": 0,
      "feederId": 87,
      "charLevel": 70
    },
    {
      "id": 61,
      "name": "Invisible Woman (Classic)",
      "image": "#",
      "rarity": 4,
      "powerOneLevel": 0,
      "powerTwoLevel": 0,
      "powerThreeLevel": 0,
      "powerOneColor": "yellow",
      "powerTwoColor": "blue",
      "powerThreeColor": "green",
      "feedeeId": 0,
      "feederId": 36,
      "charLevel": 70
    },
    {
      "id": 62,
      "name": "Iron Fist (Immortal Weapon)",
      "image": "#",
      "rarity": 3,
      "powerOneLevel": 0,
      "powerTwoLevel": 0,
      "powerThreeLevel": 0,
      "powerOneColor": "green",
      "powerTwoColor": "purple",
      "powerThreeColor": "black",
      "feedeeId": 63,
      "feederId": 0,
      "charLevel": 40
    },
    {
      "id": 63,
      "name": "Iron Fist (Danny Rand)",
      "image": "#",
      "rarity": 4,
      "powerOneLevel": 0,
      "powerTwoLevel": 0,
      "powerThreeLevel": 0,
      "powerOneColor": "blue",
      "powerTwoColor": "green",
      "powerThreeColor": "black",
      "feedeeId": 0,
      "feederId": 62,
      "charLevel": 70
    },
    {
      "id": 64,
      "name": "Iron Man (Mark XLVI)",
      "image": "#",
      "rarity": 5,
      "powerOneLevel": 0,
      "powerTwoLevel": 0,
      "powerThreeLevel": 0,
      "powerOneColor": "yellow",
      "powerTwoColor": "red",
      "powerThreeColor": "blue",
      "feedeeId": 0,
      "feederId": 132,
      "charLevel": 255
    },
    {
      "id": 65,
      "name": "Iron Man (Model 40)",
      "image": "#",
      "rarity": 3,
      "powerOneLevel": 0,
      "powerTwoLevel": 0,
      "powerThreeLevel": 0,
      "powerOneColor": "red",
      "powerTwoColor": "blue",
      "powerThreeColor": "yellow",
      "feedeeId": 66,
      "feederId": 0,
      "charLevel": 40
    },
    {
      "id": 66,
      "name": "Iron Man (Hulkbuster)",
      "image": "#",
      "rarity": 5,
      "powerOneLevel": 0,
      "powerTwoLevel": 0,
      "powerThreeLevel": 0,
      "powerOneColor": "red",
      "powerTwoColor": "black",
      "powerThreeColor": "blue",
      "feedeeId": 0,
      "feederId": 65,
      "charLevel": 255
    },
    {
      "id": 67,
      "name": "Jean Grey (Phoenix)",
      "image": "#",
      "rarity": 5,
      "powerOneLevel": 0,
      "powerTwoLevel": 0,
      "powerThreeLevel": 0,
      "powerOneColor": "green",
      "powerTwoColor": "purple",
      "powerThreeColor": "red",
      "feedeeId": 0,
      "feederId": 70,
      "charLevel": 255
    },
    {
      "id": 68,
      "name": "Jean Grey (All New X-Men)",
      "image": "#",
      "rarity": 4,
      "powerOneLevel": 0,
      "powerTwoLevel": 0,
      "powerThreeLevel": 0,
      "powerOneColor": "green",
      "powerTwoColor": "purple",
      "powerThreeColor": "blue",
      "feedeeId": 0,
      "feederId": [2, 5],
      "charLevel": 70
    },
    {
      "id": 69,
      "name": "Jessica Jones (Alias Investigations)",
      "image": "#",
      "rarity": 5,
      "powerOneLevel": 0,
      "powerTwoLevel": 0,
      "powerThreeLevel": 0,
      "powerOneColor": "red",
      "powerTwoColor": "black",
      "powerThreeColor": "blue",
      "feedeeId": 0,
      "feederId": 1,
      "charLevel": 255
    },
    {
      "id": 70,
      "name": "Jubilee (Uncanny X-Men)",
      "image": "#",
      "rarity": 4,
      "powerOneLevel": 0,
      "powerTwoLevel": 0,
      "powerThreeLevel": 0,
      "powerOneColor": "yellow",
      "powerTwoColor": "purple",
      "powerThreeColor": "green",
      "feedeeId": 67,
      "feederId": 0,
      "charLevel": 70
    },
    {
      "id": 71,
      "name": "Kamala Khan (Ms. Marvel)",
      "image": "#",
      "rarity": 3,
      "powerOneLevel": 0,
      "powerTwoLevel": 0,
      "powerThreeLevel": 0,
      "powerOneColor": "yellow",
      "powerTwoColor": "purple",
      "powerThreeColor": "green",
      "feedeeId": 81,
      "feederId": 0,
      "charLevel": 40
    },
    {
      "id": 72,
      "name": "Kate Bishop (Hawkeye)",
      "image": "#",
      "rarity": 4,
      "powerOneLevel": 0,
      "powerTwoLevel": 0,
      "powerThreeLevel": 0,
      "powerOneColor": "blue",
      "powerTwoColor": "black",
      "powerThreeColor": "purple",
      "feedeeId": 51,
      "feederId": 52,
      "charLevel": 70
    },
    {
      "id": 73,
      "name": "Kingpin (Spider-Verse)",
      "image": "#",
      "rarity": 5,
      "powerOneLevel": 0,
      "powerTwoLevel": 0,
      "powerThreeLevel": 0,
      "powerOneColor": "blue",
      "powerTwoColor": "black",
      "powerThreeColor": "purple",
      "feedeeId": 0,
      "feederId": 82,
      "charLevel": 255
    },
    {
      "id": 74,
      "name": "Kingpin (Wilson Fisk)",
      "image": "#",
      "rarity": 4,
      "powerOneLevel": 0,
      "powerTwoLevel": 0,
      "powerThreeLevel": 0,
      "powerOneColor": "black",
      "powerTwoColor": "purple",
      "powerThreeColor": "yellow",
      "feedeeId": 33,
      "feederId": 17,
      "charLevel": 70
    },
    {
      "id": 75,
      "name": "Loki (God of Mischief)",
      "image": "#",
      "rarity": 5,
      "powerOneLevel": 0,
      "powerTwoLevel": 0,
      "powerThreeLevel": 0,
      "powerOneColor": "purple",
      "powerTwoColor": "green",
      "powerThreeColor": "black",
      "feedeeId": 0,
      "feederId": 59,
      "charLevel": 255
    },
    {
      "id": 76,
      "name": "Loki (Dark Reign)",
      "image": "#",
      "rarity": 3,
      "powerOneLevel": 0,
      "powerTwoLevel": 0,
      "powerThreeLevel": 0,
      "powerOneColor": "black",
      "powerTwoColor": "purple",
      "powerThreeColor": "green",
      "feedeeId": 129,
      "feederId": 0,
      "charLevel": 40
    },
    {
      "id": 77,
      "name": "Luke Cage (Hero For Hire)",
      "image": "#",
      "rarity": 3,
      "powerOneLevel": 0,
      "powerTwoLevel": 0,
      "powerThreeLevel": 0,
      "powerOneColor": "yellow",
      "powerTwoColor": "red",
      "powerThreeColor": "black",
      "feedeeId": 78,
      "feederId": 0,
      "charLevel": 40
    },
    {
      "id": 78,
      "name": "Luke Cage (Power Man)",
      "image": "#",
      "rarity": 4,
      "powerOneLevel": 0,
      "powerTwoLevel": 0,
      "powerThreeLevel": 0,
      "powerOneColor": "yellow",
      "powerTwoColor": "black",
      "powerThreeColor": "red",
      "feedeeId": 0,
      "feederId": 77,
      "charLevel": 70
    },
    {
      "id": 79,
      "name": "Magneto (Marvel NOW!)",
      "image": "#",
      "rarity": 2,
      "powerOneLevel": 0,
      "powerTwoLevel": 0,
      "powerThreeLevel": 0,
      "powerOneColor": "blue",
      "powerTwoColor": "purple",
      "powerThreeColor": "red",
      "feedeeId": 80,
      "feederId": 0,
      "charLevel": 15
    },
    {
      "id": 80,
      "name": "Magneto (Classic)",
      "image": "#",
      "rarity": 3,
      "powerOneLevel": 0,
      "powerTwoLevel": 0,
      "powerThreeLevel": 0,
      "powerOneColor": "red",
      "powerTwoColor": "blue",
      "powerThreeColor": "yellow",
      "feedeeId": 92,
      "feederId": 79,
      "charLevel": 40
    },
    {
      "id": 81,
      "name": "Medusa (Inhuman Queen)",
      "image": "#",
      "rarity": 4,
      "powerOneLevel": 0,
      "powerTwoLevel": 0,
      "powerThreeLevel": 0,
      "powerOneColor": "black",
      "powerTwoColor": "purple",
      "powerThreeColor": "green",
      "feedeeId": 6,
      "feederId": 71,
      "charLevel": 70
    },
    {
      "id": 82,
      "name": " Miles Morales (Spider-Man)",
      "image": "#",
      "rarity": 4,
      "powerOneLevel": 0,
      "powerTwoLevel": 0,
      "powerThreeLevel": 0,
      "powerOneColor": "purple",
      "powerTwoColor": "yellow",
      "powerThreeColor": "red",
      "feedeeId": 73,
      "feederId": 111,
      "charLevel": 70
    },
    {
      "id": 83,
      "name": "Moon Knight (Marc Spector)",
      "image": "#",
      "rarity": 4,
      "powerOneLevel": 0,
      "powerTwoLevel": 0,
      "powerThreeLevel": 0,
      "powerOneColor": "black",
      "powerTwoColor": "purple",
      "powerThreeColor": "green",
      "feedeeId": 0,
      "feederId": 104,
      "charLevel": 70
    },
    {
      "id": 84,
      "name": "Moonstone (Dark Avengers)",
      "image": "#",
      "rarity": 2,
      "powerOneLevel": 0,
      "powerTwoLevel": 0,
      "powerThreeLevel": 0,
      "powerOneColor": "purple",
      "powerTwoColor": "black",
      "powerThreeColor": "red",
      "feedeeId": 57,
      "feederId": 0,
      "charLevel": 15
    },
    {
      "id": 85,
      "name": "Mordo (Master of the Mystic Arts)",
      "image": "#",
      "rarity": 5,
      "powerOneLevel": 0,
      "powerTwoLevel": 0,
      "powerThreeLevel": 0,
      "powerOneColor": "black",
      "powerTwoColor": "blue",
      "powerThreeColor": "purple",
      "feedeeId": 40,
      "feederId": 0,
      "charLevel": 15
    },
    {
      "id": 86,
      "name": "Mr. Fantastic (Reed Richards)",
      "image": "#",
      "rarity": 4,
      "powerOneLevel": 0,
      "powerTwoLevel": 0,
      "powerThreeLevel": 0,
      "powerOneColor": "blue",
      "powerTwoColor": "yellow",
      "powerThreeColor": "black",
      "feedeeId": 108,
      "feederId": 0,
      "charLevel": 70
    },
    {
      "id": 87,
      "name": "Mystique (Raven Darkholme)",
      "image": "#",
      "rarity": 3,
      "powerOneLevel": 0,
      "powerTwoLevel": 0,
      "powerThreeLevel": 0,
      "powerOneColor": "purple",
      "powerTwoColor": "blue",
      "powerThreeColor": "black",
      "feedeeId": 60,
      "feederId": 0,
      "charLevel": 40
    },
    {
      "id": 88,
      "name": "Nick Fury (Director of S.H.I.E.L.D.)",
      "image": "#",
      "rarity": 4,
      "powerOneLevel": 0,
      "powerTwoLevel": 0,
      "powerThreeLevel": 0,
      "powerOneColor": "blue",
      "powerTwoColor": "yellow",
      "powerThreeColor": "purple",
      "feedeeId": 0,
      "feederId": 12,
      "charLevel": 70
    },
    {
      "id": 89,
      "name": "Nova (Sam Alexander)",
      "image": "#",
      "rarity": 5,
      "powerOneLevel": 0,
      "powerTwoLevel": 0,
      "powerThreeLevel": 0,
      "powerOneColor": "red",
      "powerTwoColor": "yellow",
      "powerThreeColor": "black",
      "feedeeId": 0,
      "feederId": 39,
      "charLevel": 70
    },
    {
      "id": 90,
      "name": "Okoye (Warrior General)",
      "image": "#",
      "rarity": 5,
      "powerOneLevel": 0,
      "powerTwoLevel": 0,
      "powerThreeLevel": 0,
      "powerOneColor": "black",
      "powerTwoColor": "yellow",
      "powerThreeColor": "red",
      "feedeeId": 0,
      "feederId": 107,
      "charLevel": 255
    },
    {
      "id": 91,
      "name": "Peggy Carter (Captain America)",
      "image": "#",
      "rarity": 5,
      "powerOneLevel": 0,
      "powerTwoLevel": 0,
      "powerThreeLevel": 0,
      "powerOneColor": "red",
      "powerTwoColor": "yellow",
      "powerThreeColor": "blue",
      "feedeeId": 18,
      "feederId": 12,
      "charLevel": 15
    },
    {
      "id": 92,
      "name": "Professor X (Charles Xavier)",
      "image": "#",
      "rarity": 4,
      "powerOneLevel": 0,
      "powerTwoLevel": 0,
      "powerThreeLevel": 0,
      "powerOneColor": "blue",
      "powerTwoColor": "purple",
      "powerThreeColor": "yellow",
      "feedeeId": 0,
      "feederId": 80,
      "charLevel": 70
    },
    {
      "id": 93,
      "name": "The Punisher (Dark Reign)",
      "image": "#",
      "rarity": 3,
      "powerOneLevel": 0,
      "powerTwoLevel": 0,
      "powerThreeLevel": 0,
      "powerOneColor": "black",
      "powerTwoColor": "green",
      "powerThreeColor": "red",
      "feedeeId": 94,
      "feederId": 0,
      "charLevel": 40
    },
    {
      "id": 94,
      "name": "The Punisher (MAX)",
      "image": "#",
      "rarity": 4,
      "powerOneLevel": 0,
      "powerTwoLevel": 0,
      "powerThreeLevel": 0,
      "powerOneColor": "black",
      "powerTwoColor": "green",
      "powerThreeColor": "blue",
      "feedeeId": 0,
      "feederId": 12,
      "charLevel": 70
    },
    {
      "id": 95,
      "name": "Quake (Daisy Johnson)",
      "image": "#",
      "rarity": 4,
      "powerOneLevel": 0,
      "powerTwoLevel": 0,
      "powerThreeLevel": 0,
      "powerOneColor": "green",
      "powerTwoColor": "yellow",
      "powerThreeColor": "blue",
      "feedeeId": 0,
      "feederId": 104,
      "charLevel": 70
    },
    {
      "id": 96,
      "name": "Quicksilver (Pietro Maximoff)",
      "image": "#",
      "rarity": 3,
      "powerOneLevel": 0,
      "powerTwoLevel": 0,
      "powerThreeLevel": 0,
      "powerOneColor": "black",
      "powerTwoColor": "blue",
      "powerThreeColor": "green",
      "feedeeId": 132,
      "feederId": 0,
      "charLevel": 40
    },
    {
      "id": 97,
      "name": "Ragnarok (Dark Avengers)",
      "image": "#",
      "rarity": 5,
      "powerOneLevel": 0,
      "powerTwoLevel": 0,
      "powerThreeLevel": 0,
      "powerOneColor": "blue",
      "powerTwoColor": "green",
      "powerThreeColor": "red",
      "feedeeId": 140,
      "feederId": 4,
      "charLevel": 40
    },
    {
      "id": 98,
      "name": "Red Hulk (Thunderbolt Ross)",
      "image": "#",
      "rarity": 5,
      "powerOneLevel": 0,
      "powerTwoLevel": 0,
      "powerThreeLevel": 0,
      "powerOneColor": "red",
      "powerTwoColor": "green",
      "powerThreeColor": "purple",
      "feedeeId": 0,
      "feederId": 126,
      "charLevel": 15
    },
    {
      "id": 99,
      "name": "Rocket & Groot (Most Wanted)",
      "image": "#",
      "rarity": 3,
      "powerOneLevel": 0,
      "powerTwoLevel": 0,
      "powerThreeLevel": 0,
      "powerOneColor": "yellow",
      "powerTwoColor": "green",
      "powerThreeColor": "blue",
      "feedeeId": 41,
      "feederId": 0,
      "charLevel": 40
    },
    {
      "id": 100,
      "name": "Rogue (Classic)",
      "image": "#",
      "rarity": 4,
      "powerOneLevel": 0,
      "powerTwoLevel": 0,
      "powerThreeLevel": 0,
      "powerOneColor": "green",
      "powerTwoColor": "red",
      "powerThreeColor": "yellow",
      "feedeeId": 0,
      "feederId": 44,
      "charLevel": 70
    },
    {
      "id": 101,
      "name": "Sam Wilson (Falcon)",
      "image": "#",
      "rarity": 5,
      "powerOneLevel": 0,
      "powerTwoLevel": 0,
      "powerThreeLevel": 0,
      "powerOneColor": "yellow",
      "powerTwoColor": "blue",
      "powerThreeColor": "purple",
      "feedeeId": 0,
      "feederId": 12,
      "charLevel": 15
    },
    {
      "id": 102,
      "name": "Sam Wilson (Captain America)",
      "image": "#",
      "rarity": 4,
      "powerOneLevel": 0,
      "powerTwoLevel": 0,
      "powerThreeLevel": 0,
      "powerOneColor": "yellow",
      "powerTwoColor": "blue",
      "powerThreeColor": "red",
      "feedeeId": 0,
      "feederId": 101,
      "charLevel": 70
    },
    {
      "id": 103,
      "name": "Sandman (Flint Marko)",
      "image": "#",
      "rarity": 4,
      "powerOneLevel": 0,
      "powerTwoLevel": 0,
      "powerThreeLevel": 0,
      "powerOneColor": "green",
      "powerTwoColor": "purple",
      "powerThreeColor": "yellow",
      "feedeeId": 49,
      "feederId": 0,
      "charLevel": 70
    },
    {
      "id": 104,
      "name": "Scarlet Witch (Wanda Maximoff)",
      "image": "#",
      "rarity": 3,
      "powerOneLevel": 0,
      "powerTwoLevel": 0,
      "powerThreeLevel": 0,
      "powerOneColor": "purple",
      "powerTwoColor": "green",
      "powerThreeColor": "blue",
      "feedeeId": 95,
      "feederId": 0,
      "charLevel": 40
    },
    {
      "id": 105,
      "name": "Sentry (Dark Avengers)",
      "image": "#",
      "rarity": 3,
      "powerOneLevel": 0,
      "powerTwoLevel": 0,
      "powerThreeLevel": 0,
      "powerOneColor": "red",
      "powerTwoColor": "green",
      "powerThreeColor": "yellow",
      "feedeeId": 83,
      "feederId": 12,
      "charLevel": 40
    },
    {
      "id": 106,
      "name": "She-Hulk (Modern)",
      "image": "#",
      "rarity": 3,
      "powerOneLevel": 0,
      "powerTwoLevel": 0,
      "powerThreeLevel": 0,
      "powerOneColor": "blue",
      "powerTwoColor": "green",
      "powerThreeColor": "red",
      "feedeeId": 50,
      "feederId": 0,
      "charLevel": 40
    },
    {
      "id": 107,
      "name": "Shuri (Master Engineer)",
      "image": "#",
      "rarity": 4,
      "powerOneLevel": 0,
      "powerTwoLevel": 0,
      "powerThreeLevel": 0,
      "powerOneColor": "blue",
      "powerTwoColor": "green",
      "powerThreeColor": "red",
      "feedeeId": 90,
      "feederId": 0,
      "charLevel": 70
    },
    {
      "id": 108,
      "name": "Silver Surfer (Skyrider)",
      "image": "#",
      "rarity": 5,
      "powerOneLevel": 0,
      "powerTwoLevel": 0,
      "powerThreeLevel": 0,
      "powerOneColor": "blue",
      "powerTwoColor": "red",
      "powerThreeColor": "black",
      "feedeeId": 0,
      "feederId": 86,
      "charLevel": 255
    },
    {
      "id": 109,
      "name": "Spider-Man (Bag-Man)",
      "image": "#",
      "rarity": 5,
      "powerOneLevel": 0,
      "powerTwoLevel": 0,
      "powerThreeLevel": 0,
      "powerOneColor": "purple",
      "powerTwoColor": "blue",
      "powerThreeColor": "yellow",
      "feedeeId": 111,
      "feederId": 0,
      "charLevel": 15
    },
    {
      "id": 110,
      "name": "Spider-Man (Back In Black)",
      "image": "#",
      "rarity": 5,
      "powerOneLevel": 0,
      "powerTwoLevel": 0,
      "powerThreeLevel": 0,
      "powerOneColor": "blue",
      "powerTwoColor": "green",
      "powerThreeColor": "purple",
      "feedeeId": 0,
      "feederId": 12,
      "charLevel": 255
    },
    {
      "id": 111,
      "name": "Spider-Man (Classic)",
      "image": "#",
      "rarity": 3,
      "powerOneLevel": 0,
      "powerTwoLevel": 0,
      "powerThreeLevel": 0,
      "powerOneColor": "purple",
      "powerTwoColor": "yellow",
      "powerThreeColor": "blue",
      "feedeeId": 0,
      "feederId": 12,
      "charLevel": 40
    },
    {
      "id": 112,
      "name": "Spider-Man (Infinity War)",
      "image": "#",
      "rarity": 5,
      "powerOneLevel": 0,
      "powerTwoLevel": 0,
      "powerThreeLevel": 0,
      "powerOneColor": "blue",
      "powerTwoColor": "green",
      "powerThreeColor": "red",
      "feedeeId": 0,
      "feederId": 12,
      "charLevel": 15
    },
    {
      "id": 113,
      "name": "Spider-Man (Peter Parker)",
      "image": "#",
      "rarity": 5,
      "powerOneLevel": 0,
      "powerTwoLevel": 0,
      "powerThreeLevel": 0,
      "powerOneColor": "blue",
      "powerTwoColor": "green",
      "powerThreeColor": "red",
      "feedeeId": 0,
      "feederId": 131,
      "charLevel": 255
    },
    {
      "id": 114,
      "name": "Spider-Woman (Jessica Drew)",
      "image": "#",
      "rarity": 4,
      "powerOneLevel": 0,
      "powerTwoLevel": 0,
      "powerThreeLevel": 0,
      "powerOneColor": "black",
      "powerTwoColor": "purple",
      "powerThreeColor": "red",
      "feedeeId": 0,
      "feederId": 122,
      "charLevel": 70
    },
    {
      "id": 115,
      "name": "Squirrel-Girl (Unbeatable)",
      "image": "#",
      "rarity": 3,
      "powerOneLevel": 0,
      "powerTwoLevel": 0,
      "powerThreeLevel": 0,
      "powerOneColor": "yellow",
      "powerTwoColor": "purple",
      "powerThreeColor": "green",
      "feedeeId": 3,
      "feederId": 0,
      "charLevel": 40
    },
    {
      "id": 116,
      "name": "Star-Lord (Awesome Mix Volume 2)",
      "image": "#",
      "rarity": 5,
      "powerOneLevel": 0,
      "powerTwoLevel": 0,
      "powerThreeLevel": 0,
      "powerOneColor": "yellow",
      "powerTwoColor": "purple",
      "powerThreeColor": "green",
      "feedeeId": 0,
      "feederId": 41,
      "charLevel": 255
    },
    {
      "id": 117,
      "name": "Star-Lord (Legendary Outlaw)",
      "image": "#",
      "rarity": 4,
      "powerOneLevel": 0,
      "powerTwoLevel": 0,
      "powerThreeLevel": 0,
      "powerOneColor": "purple",
      "powerTwoColor": "yellow",
      "powerThreeColor": "red",
      "feedeeId": 0,
      "feederId": [45, 118],
      "charLevel": 40
    },
    {
      "id": 118,
      "name": "Star-Lord (Peter Quill)",
      "image": "#",
      "rarity": 3,
      "powerOneLevel": 0,
      "powerTwoLevel": 0,
      "powerThreeLevel": 0,
      "powerOneColor": "purple",
      "powerTwoColor": "yellow",
      "powerThreeColor": "red",
      "feedeeId": 117,
      "feederId": 0,
      "charLevel": 40
    },
    {
      "id": 119,
      "name": "Storm (Classic)",
      "image": "#",
      "rarity": 2,
      "powerOneLevel": 0,
      "powerTwoLevel": 0,
      "powerThreeLevel": 0,
      "powerOneColor": "green",
      "powerTwoColor": "blue",
      "powerThreeColor": "yellow",
      "feedeeId": 120,
      "feederId": 0,
      "charLevel": 15
    },
    {
      "id": 120,
      "name": "Storm (Mohawk)",
      "image": "#",
      "rarity": 5,
      "powerOneLevel": 0,
      "powerTwoLevel": 0,
      "powerThreeLevel": 0,
      "powerOneColor": "green",
      "powerTwoColor": "yellow",
      "powerThreeColor": "black",
      "feedeeId": 124,
      "feederId": 119,
      "charLevel": 15
    },
    {
      "id": 121,
      "name": "Thanos (The Mad Titan)",
      "image": "#",
      "rarity": 5,
      "powerOneLevel": 0,
      "powerTwoLevel": 0,
      "powerThreeLevel": 0,
      "powerOneColor": "black",
      "powerTwoColor": "purple",
      "powerThreeColor": "green",
      "feedeeId": 0,
      "feederId": 46,
      "charLevel": 255
    },
    {
      "id": 122,
      "name": "Thanos (Modern)",
      "image": "#",
      "rarity": 3,
      "powerOneLevel": 0,
      "powerTwoLevel": 0,
      "powerThreeLevel": 0,
      "powerOneColor": "black",
      "powerTwoColor": "purple",
      "powerThreeColor": "green",
      "feedeeId": 114,
      "feederId": 0,
      "charLevel": 40
    },
    {
      "id": 123,
      "name": "The Thing (Classic)",
      "image": "#",
      "rarity": 4,
      "powerOneLevel": 0,
      "powerTwoLevel": 0,
      "powerThreeLevel": 0,
      "powerOneColor": "red",
      "powerTwoColor": "yellow",
      "powerThreeColor": "green",
      "feedeeId": 0,
      "feederId": 55,
      "charLevel": 70
    },
    {
      "id": 124,
      "name": "Thor (Goddess of Thunder)",
      "image": "#",
      "rarity": 4,
      "powerOneLevel": 0,
      "powerTwoLevel": 0,
      "powerThreeLevel": 0,
      "powerOneColor": "red",
      "powerTwoColor": "yellow",
      "powerThreeColor": "blue",
      "feedeeId": 0,
      "feederId": 120,
      "charLevel": 255
    },
    {
      "id": 125,
      "name": "Thor (Marvel NOW!)",
      "image": "#",
      "rarity": 2,
      "powerOneLevel": 0,
      "powerTwoLevel": 0,
      "powerThreeLevel": 0,
      "powerOneColor": "red",
      "powerTwoColor": "yellow",
      "powerThreeColor": "green",
      "feedeeId": 126,
      "feederId": 0,
      "charLevel": 15
    },
    {
      "id": 126,
      "name": "Thor (Modern)",
      "image": "#",
      "rarity": 3,
      "powerOneLevel": 0,
      "powerTwoLevel": 0,
      "powerThreeLevel": 0,
      "powerOneColor": "red",
      "powerTwoColor": "yellow",
      "powerThreeColor": "green",
      "feedeeId": 98,
      "feederId": 125,
      "charLevel": 40
    },
    {
      "id": 127,
      "name": "Thor (Gladiator)",
      "image": "#",
      "rarity": 5,
      "powerOneLevel": 0,
      "powerTwoLevel": 0,
      "powerThreeLevel": 0,
      "powerOneColor": "green",
      "powerTwoColor": "red",
      "powerThreeColor": "yellow",
      "feedeeId": 0,
      "feederId": 128,
      "charLevel": 255
    },
    {
      "id": 128,
      "name": "Valkyrie (Asgardian Warrior)",
      "image": "#",
      "rarity": 4,
      "powerOneLevel": 0,
      "powerTwoLevel": 0,
      "powerThreeLevel": 0,
      "powerOneColor": "red",
      "powerTwoColor": "black",
      "powerThreeColor": "yellow",
      "feedeeId": 128,
      "feederId": 0,
      "charLevel": 70
    },
    {
      "id": 129,
      "name": "Venom (Eddie Brock)",
      "image": "#",
      "rarity": 3,
      "powerOneLevel": 0,
      "powerTwoLevel": 0,
      "powerThreeLevel": 0,
      "powerOneColor": "green",
      "powerTwoColor": "black",
      "powerThreeColor": "yellow",
      "feedeeId": 0,
      "feederId": 76,
      "charLevel": 70
    },
    {
      "id": 130,
      "name": "Vision (Android Avenger)",
      "image": "#",
      "rarity": 3,
      "powerOneLevel": 0,
      "powerTwoLevel": 0,
      "powerThreeLevel": 0,
      "powerOneColor": "blue",
      "powerTwoColor": "red",
      "powerThreeColor": "yellow",
      "feedeeId": 134,
      "feederId": 0,
      "charLevel": 40
    },
    {
      "id": 131,
      "name": "Vulture (Adrian Toomes)",
      "image": "#",
      "rarity": 5,
      "powerOneLevel": 0,
      "powerTwoLevel": 0,
      "powerThreeLevel": 0,
      "powerOneColor": "black",
      "powerTwoColor": "green",
      "powerThreeColor": "blue",
      "feedeeId": 113,
      "feederId": 0,
      "charLevel": 15
    },
    {
      "id": 132,
      "name": "War Machine (James Rhodes)",
      "image": "#",
      "rarity": 5,
      "powerOneLevel": 0,
      "powerTwoLevel": 0,
      "powerThreeLevel": 0,
      "powerOneColor": "red",
      "powerTwoColor": "blue",
      "powerThreeColor": "green",
      "feedeeId": 0,
      "feederId": 96,
      "charLevel": 15
    },
    {
      "id": 133,
      "name": "Wasp (Hope Van Dyne)",
      "image": "#",
      "rarity": 5,
      "powerOneLevel": 0,
      "powerTwoLevel": 0,
      "powerThreeLevel": 0,
      "powerOneColor": "blue",
      "powerTwoColor": "yellow",
      "powerThreeColor": "black",
      "feedeeId": 0,
      "feederId": 3,
      "charLevel": 255
    },
    {
      "id": 134,
      "name": "Wasp (Janet Van Dyne)",
      "image": "#",
      "rarity": 5,
      "powerOneLevel": 0,
      "powerTwoLevel": 0,
      "powerThreeLevel": 0,
      "powerOneColor": "yellow",
      "powerTwoColor": "blue",
      "powerThreeColor": "black",
      "feedeeId": 0,
      "feederId": 130,
      "charLevel": 255
    },
    {
      "id": 135,
      "name": "Winter Soldier (Bucky Barnes)",
      "image": "#",
      "rarity": 4,
      "powerOneLevel": 0,
      "powerTwoLevel": 0,
      "powerThreeLevel": 0,
      "powerOneColor": "purple",
      "powerTwoColor": "blue",
      "powerThreeColor": "red",
      "feedeeId": 19,
      "feederId": 20,
      "charLevel": 70
    },
    {
      "id": 136,
      "name": "Wolverine (Astonishing X-Men)",
      "image": "#",
      "rarity": 5,
      "powerOneLevel": 0,
      "powerTwoLevel": 0,
      "powerThreeLevel": 0,
      "powerOneColor": "green",
      "powerTwoColor": "red",
      "powerThreeColor": "yellow",
      "feedeeId": 137,
      "feederId": 0,
      "charLevel": 15
    },
    {
      "id": 137,
      "name": "Wolverine (Patch)",
      "image": "#",
      "rarity": 5,
      "powerOneLevel": 0,
      "powerTwoLevel": 0,
      "powerThreeLevel": 0,
      "powerOneColor": "green",
      "powerTwoColor": "red",
      "powerThreeColor": "yellow",
      "feedeeId": 139,
      "feederId": 136,
      "charLevel": 15
    },
    {
      "id": 138,
      "name": "Wolverine (Old Man Logan)",
      "image": "#",
      "rarity": 5,
      "powerOneLevel": 0,
      "powerTwoLevel": 0,
      "powerThreeLevel": 0,
      "powerOneColor": "black",
      "powerTwoColor": "yellow",
      "powerThreeColor": "red",
      "feedeeId": 0,
      "feederId": 139,
      "charLevel": 15
    },
    {
      "id": 139,
      "name": "Wolverine (X-Force)",
      "image": "#",
      "rarity": 4,
      "powerOneLevel": 0,
      "powerTwoLevel": 0,
      "powerThreeLevel": 0,
      "powerOneColor": "green",
      "powerTwoColor": "black",
      "powerThreeColor": "yellow",
      "feedeeId": 139,
      "feederId": [27, 137],
      "charLevel": 70
    },
    {
      "id": 140,
      "name": "X-23 (All-New Wolverine)",
      "image": "#",
      "rarity": 4,
      "powerOneLevel": 0,
      "powerTwoLevel": 0,
      "powerThreeLevel": 0,
      "powerOneColor": "green",
      "powerTwoColor": "red",
      "powerThreeColor": "purple",
      "feedeeId": 0,
      "feederId": [31, 97],
      "charLevel": 255
    }
  ]
}
